project_demo/__init__.py
project_demo/data_prep/__init__.py
project_demo/data_prep/prep_data.py
project_demo/main.py
project_demo/model/__init__.py
project_demo/model/train_model.py
project_demo_juhi-0.1.2.4.dist-info/METADATA
project_demo_juhi-0.1.2.4.dist-info/WHEEL
project_demo_juhi-0.1.2.4.dist-info/RECORD
